[
  {
    "id": "9607805924",
    "title": "Kicking it off with a Sunday Salad",
    "description": "",
    "heightAsPercentageOfWidth": 66,
    "url": "/beaver-brook/photos/9607805924-original.jpg",
    "sizes": {
      "large": {
        "label": "Large",
        "width": 1024,
        "height": 685,
        "source": "/beaver-brook/photos/9607805924-large.jpg",
        "photo": true
      },
      "original": {
        "label": "Original",
        "width": 3872,
        "height": 2592,
        "source": "/beaver-brook/photos/9607805924-original.jpg",
        "photo": true
      }
    }
  },
  {
    "id": "9607765980",
    "title": "The Sauna Site; Piers Installed",
    "description": "",
    "heightAsPercentageOfWidth": 66,
    "url": "/beaver-brook/photos/9607765980-original.jpg",
    "sizes": {
      "large": {
        "label": "Large",
        "width": 685,
        "height": 1024,
        "source": "/beaver-brook/photos/9607765980-large.jpg",
        "photo": true
      },
      "original": {
        "label": "Original",
        "width": 3872,
        "height": 2592,
        "source": "/beaver-brook/photos/9607765980-original.jpg",
        "photo": true
      }
    }
  },
  {
    "id": "9608050358",
    "title": "Alli Sparks It",
    "description": "",
    "heightAsPercentageOfWidth": 66,
    "url": "/beaver-brook/photos/9608050358-original.jpg",
    "sizes": {
      "large": {
        "label": "Large",
        "width": 1024,
        "height": 685,
        "source": "/beaver-brook/photos/9608050358-large.jpg",
        "photo": true
      },
      "original": {
        "label": "Original",
        "width": 3872,
        "height": 2592,
        "source": "/beaver-brook/photos/9608050358-original.jpg",
        "photo": true
      }
    }
  },
  {
    "id": "9607785032",
    "title": "Armin finishes the Benchmark Post",
    "description": "",
    "heightAsPercentageOfWidth": 66,
    "url": "/beaver-brook/photos/9607785032-original.jpg",
    "sizes": {
      "large": {
        "label": "Large",
        "width": 685,
        "height": 1024,
        "source": "/beaver-brook/photos/9607785032-large.jpg",
        "photo": true
      },
      "original": {
        "label": "Original",
        "width": 3872,
        "height": 2592,
        "source": "/beaver-brook/photos/9607785032-original.jpg",
        "photo": true
      }
    }
  },
  {
    "id": "9608026644",
    "title": "Armin Levels the Circular Saw Blade",
    "description": "",
    "heightAsPercentageOfWidth": 66,
    "url": "/beaver-brook/photos/9608026644-original.jpg",
    "sizes": {
      "large": {
        "label": "Large",
        "width": 1024,
        "height": 685,
        "source": "/beaver-brook/photos/9608026644-large.jpg",
        "photo": true
      },
      "original": {
        "label": "Original",
        "width": 3872,
        "height": 2592,
        "source": "/beaver-brook/photos/9608026644-original.jpg",
        "photo": true
      }
    }
  },
  {
    "id": "9604714031",
    "title": "Errbody Workin'",
    "description": "",
    "heightAsPercentageOfWidth": 66,
    "url": "/beaver-brook/photos/9604714031-original.jpg",
    "sizes": {
      "large": {
        "label": "Large",
        "width": 1024,
        "height": 685,
        "source": "/beaver-brook/photos/9604714031-large.jpg",
        "photo": true
      },
      "original": {
        "label": "Original",
        "width": 3872,
        "height": 2592,
        "source": "/beaver-brook/photos/9604714031-original.jpg",
        "photo": true
      }
    }
  },
  {
    "id": "9604838797",
    "title": "Abercrombie Types",
    "description": "",
    "heightAsPercentageOfWidth": 66,
    "url": "/beaver-brook/photos/9604838797-original.jpg",
    "sizes": {
      "large": {
        "label": "Large",
        "width": 1024,
        "height": 685,
        "source": "/beaver-brook/photos/9604838797-large.jpg",
        "photo": true
      },
      "original": {
        "label": "Original",
        "width": 3872,
        "height": 2592,
        "source": "/beaver-brook/photos/9604838797-original.jpg",
        "photo": true
      }
    }
  },
  {
    "id": "9604509157",
    "title": "Walking on the Sawhorse",
    "description": "",
    "heightAsPercentageOfWidth": 66,
    "url": "/beaver-brook/photos/9604509157-original.jpg",
    "sizes": {
      "large": {
        "label": "Large",
        "width": 1024,
        "height": 685,
        "source": "/beaver-brook/photos/9604509157-large.jpg",
        "photo": true
      },
      "original": {
        "label": "Original",
        "width": 3872,
        "height": 2592,
        "source": "/beaver-brook/photos/9604509157-original.jpg",
        "photo": true
      }
    }
  },
  {
    "id": "9604723213",
    "title": "dream big build small",
    "description": "",
    "heightAsPercentageOfWidth": 66,
    "url": "/beaver-brook/photos/9604723213-original.jpg",
    "sizes": {
      "large": {
        "label": "Large",
        "width": 1024,
        "height": 685,
        "source": "/beaver-brook/photos/9604723213-large.jpg",
        "photo": true
      },
      "original": {
        "label": "Original",
        "width": 3872,
        "height": 2592,
        "source": "/beaver-brook/photos/9604723213-original.jpg",
        "photo": true
      }
    }
  },
  {
    "id": "9604737683",
    "title": "Crossing the Suspension Bridge",
    "description": "",
    "heightAsPercentageOfWidth": 133,
    "url": "/beaver-brook/photos/9604737683-original.jpg",
    "sizes": {
      "large": {
        "label": "Large",
        "width": 768,
        "height": 1024,
        "source": "/beaver-brook/photos/9604737683-large.jpg",
        "photo": true
      },
      "original": {
        "label": "Original",
        "width": 2448,
        "height": 3264,
        "source": "/beaver-brook/photos/9604737683-original.jpg",
        "photo": true
      }
    }
  },
  {
    "id": "9604615427",
    "title": "On the Bridge",
    "description": "",
    "heightAsPercentageOfWidth": 133,
    "url": "/beaver-brook/photos/9604615427-original.jpg",
    "sizes": {
      "large": {
        "label": "Large",
        "width": 768,
        "height": 1024,
        "source": "/beaver-brook/photos/9604615427-large.jpg",
        "photo": true
      },
      "original": {
        "label": "Original",
        "width": 2448,
        "height": 3264,
        "source": "/beaver-brook/photos/9604615427-original.jpg",
        "photo": true
      }
    }
  },
  {
    "id": "9607761542",
    "title": "The Platform",
    "description": "",
    "heightAsPercentageOfWidth": 66,
    "url": "/beaver-brook/photos/9607761542-original.jpg",
    "sizes": {
      "large": {
        "label": "Large",
        "width": 1024,
        "height": 685,
        "source": "/beaver-brook/photos/9607761542-large.jpg",
        "photo": true
      },
      "original": {
        "label": "Original",
        "width": 3872,
        "height": 2592,
        "source": "/beaver-brook/photos/9607761542-original.jpg",
        "photo": true
      }
    }
  },
  {
    "id": "9622555599",
    "title": "A Clean Slate",
    "description": "",
    "heightAsPercentageOfWidth": 133,
    "url": "/beaver-brook/photos/9622555599-original.jpg",
    "sizes": {
      "large": {
        "label": "Large",
        "width": 768,
        "height": 1024,
        "source": "/beaver-brook/photos/9622555599-large.jpg",
        "photo": true
      },
      "original": {
        "label": "Original",
        "width": 2448,
        "height": 3264,
        "source": "/beaver-brook/photos/9622555599-original.jpg",
        "photo": true
      }
    }
  },
  {
    "id": "9625706784",
    "title": "I suck at Nailgunning",
    "description": "",
    "heightAsPercentageOfWidth": 75,
    "url": "/beaver-brook/photos/9625706784-original.jpg",
    "sizes": {
      "large": {
        "label": "Large",
        "width": 1024,
        "height": 768,
        "source": "/beaver-brook/photos/9625706784-large.jpg",
        "photo": true
      },
      "original": {
        "label": "Original",
        "width": 3264,
        "height": 2448,
        "source": "/beaver-brook/photos/9625706784-original.jpg",
        "photo": true
      }
    }
  },
  {
    "id": "9622369451",
    "title": "Zeke the Hammer",
    "description": "",
    "heightAsPercentageOfWidth": 75,
    "url": "/beaver-brook/photos/9622369451-original.jpg",
    "sizes": {
      "large": {
        "label": "Large",
        "width": 1024,
        "height": 768,
        "source": "/beaver-brook/photos/9622369451-large.jpg",
        "photo": true
      },
      "original": {
        "label": "Original",
        "width": 3264,
        "height": 2448,
        "source": "/beaver-brook/photos/9622369451-original.jpg",
        "photo": true
      }
    }
  },
  {
    "id": "9614746539",
    "title": "Hot Tub",
    "description": "",
    "heightAsPercentageOfWidth": 66,
    "url": "/beaver-brook/photos/9614746539-original.jpg",
    "sizes": {
      "large": {
        "label": "Large",
        "width": 1024,
        "height": 685,
        "source": "/beaver-brook/photos/9614746539-large.jpg",
        "photo": true
      },
      "original": {
        "label": "Original",
        "width": 3872,
        "height": 2592,
        "source": "/beaver-brook/photos/9614746539-original.jpg",
        "photo": true
      }
    }
  },
  {
    "id": "9617981754",
    "title": "Scott's Cabin",
    "description": "",
    "heightAsPercentageOfWidth": 66,
    "url": "/beaver-brook/photos/9617981754-original.jpg",
    "sizes": {
      "large": {
        "label": "Large",
        "width": 685,
        "height": 1024,
        "source": "/beaver-brook/photos/9617981754-large.jpg",
        "photo": true
      },
      "original": {
        "label": "Original",
        "width": 3872,
        "height": 2592,
        "source": "/beaver-brook/photos/9617981754-original.jpg",
        "photo": true
      }
    }
  },
  {
    "id": "9617819804",
    "title": "The Brook",
    "description": "",
    "heightAsPercentageOfWidth": 66,
    "url": "/beaver-brook/photos/9617819804-original.jpg",
    "sizes": {
      "large": {
        "label": "Large",
        "width": 685,
        "height": 1024,
        "source": "/beaver-brook/photos/9617819804-large.jpg",
        "photo": true
      },
      "original": {
        "label": "Original",
        "width": 3872,
        "height": 2592,
        "source": "/beaver-brook/photos/9617819804-original.jpg",
        "photo": true
      }
    }
  },
  {
    "id": "9617618234",
    "title": "The Box",
    "description": "",
    "heightAsPercentageOfWidth": 66,
    "url": "/beaver-brook/photos/9617618234-original.jpg",
    "sizes": {
      "large": {
        "label": "Large",
        "width": 1024,
        "height": 685,
        "source": "/beaver-brook/photos/9617618234-large.jpg",
        "photo": true
      },
      "original": {
        "label": "Original",
        "width": 3872,
        "height": 2592,
        "source": "/beaver-brook/photos/9617618234-original.jpg",
        "photo": true
      }
    }
  },
  {
    "id": "9624494549",
    "title": "A Nearly Complete Skeleton",
    "description": "",
    "heightAsPercentageOfWidth": 66,
    "url": "/beaver-brook/photos/9624494549-original.jpg",
    "sizes": {
      "large": {
        "label": "Large",
        "width": 1024,
        "height": 685,
        "source": "/beaver-brook/photos/9624494549-large.jpg",
        "photo": true
      },
      "original": {
        "label": "Original",
        "width": 3872,
        "height": 2592,
        "source": "/beaver-brook/photos/9624494549-original.jpg",
        "photo": true
      }
    }
  },
  {
    "id": "9617572084",
    "title": "Looking Out the Picture Window",
    "description": "",
    "heightAsPercentageOfWidth": 66,
    "url": "/beaver-brook/photos/9617572084-original.jpg",
    "sizes": {
      "large": {
        "label": "Large",
        "width": 1024,
        "height": 685,
        "source": "/beaver-brook/photos/9617572084-large.jpg",
        "photo": true
      },
      "original": {
        "label": "Original",
        "width": 3872,
        "height": 2592,
        "source": "/beaver-brook/photos/9617572084-original.jpg",
        "photo": true
      }
    }
  },
  {
    "id": "9624480089",
    "title": "Armin",
    "description": "",
    "heightAsPercentageOfWidth": 66,
    "url": "/beaver-brook/photos/9624480089-original.jpg",
    "sizes": {
      "large": {
        "label": "Large",
        "width": 1024,
        "height": 685,
        "source": "/beaver-brook/photos/9624480089-large.jpg",
        "photo": true
      },
      "original": {
        "label": "Original",
        "width": 3872,
        "height": 2592,
        "source": "/beaver-brook/photos/9624480089-original.jpg",
        "photo": true
      }
    }
  },
  {
    "id": "9624466575",
    "title": "Badass",
    "description": "",
    "heightAsPercentageOfWidth": 66,
    "url": "/beaver-brook/photos/9624466575-original.jpg",
    "sizes": {
      "large": {
        "label": "Large",
        "width": 1024,
        "height": 685,
        "source": "/beaver-brook/photos/9624466575-large.jpg",
        "photo": true
      },
      "original": {
        "label": "Original",
        "width": 3872,
        "height": 2592,
        "source": "/beaver-brook/photos/9624466575-original.jpg",
        "photo": true
      }
    }
  },
  {
    "id": "9627696754",
    "title": "Chef Oscar",
    "description": "",
    "heightAsPercentageOfWidth": 149,
    "url": "/beaver-brook/photos/9627696754-original.jpg",
    "sizes": {
      "large": {
        "label": "Large",
        "width": 685,
        "height": 1024,
        "source": "/beaver-brook/photos/9627696754-large.jpg",
        "photo": true
      },
      "original": {
        "label": "Original",
        "width": 2592,
        "height": 3872,
        "source": "/beaver-brook/photos/9627696754-original.jpg",
        "photo": true
      }
    }
  },
  {
    "id": "9627628482",
    "title": "Installing Rafters",
    "description": "",
    "heightAsPercentageOfWidth": 66,
    "url": "/beaver-brook/photos/9627628482-original.jpg",
    "sizes": {
      "large": {
        "label": "Large",
        "width": 1024,
        "height": 685,
        "source": "/beaver-brook/photos/9627628482-large.jpg",
        "photo": true
      },
      "original": {
        "label": "Original",
        "width": 3872,
        "height": 2592,
        "source": "/beaver-brook/photos/9627628482-original.jpg",
        "photo": true
      }
    }
  },
  {
    "id": "9624284129",
    "title": "Tech Zone",
    "description": "",
    "heightAsPercentageOfWidth": 75,
    "url": "/beaver-brook/photos/9624284129-original.jpg",
    "sizes": {
      "large": {
        "label": "Large",
        "width": 1024,
        "height": 768,
        "source": "/beaver-brook/photos/9624284129-large.jpg",
        "photo": true
      },
      "original": {
        "label": "Original",
        "width": 3264,
        "height": 2448,
        "source": "/beaver-brook/photos/9624284129-original.jpg",
        "photo": true
      }
    }
  },
  {
    "id": "9627036104",
    "title": "Barrett weilds the nailgun",
    "description": "",
    "heightAsPercentageOfWidth": 66,
    "url": "/beaver-brook/photos/9627036104-original.jpg",
    "sizes": {
      "large": {
        "label": "Large",
        "width": 1024,
        "height": 685,
        "source": "/beaver-brook/photos/9627036104-large.jpg",
        "photo": true
      },
      "original": {
        "label": "Original",
        "width": 3872,
        "height": 2592,
        "source": "/beaver-brook/photos/9627036104-original.jpg",
        "photo": true
      }
    }
  },
  {
    "id": "9631231615",
    "title": "Clyde",
    "description": "",
    "heightAsPercentageOfWidth": 66,
    "url": "/beaver-brook/photos/9631231615-original.jpg",
    "sizes": {
      "large": {
        "label": "Large",
        "width": 685,
        "height": 1024,
        "source": "/beaver-brook/photos/9631231615-large.jpg",
        "photo": true
      },
      "original": {
        "label": "Original",
        "width": 3872,
        "height": 2592,
        "source": "/beaver-brook/photos/9631231615-original.jpg",
        "photo": true
      }
    }
  },
  {
    "id": "9634279318",
    "title": "Rafters",
    "description": "",
    "heightAsPercentageOfWidth": 66,
    "url": "/beaver-brook/photos/9634279318-original.jpg",
    "sizes": {
      "large": {
        "label": "Large",
        "width": 1024,
        "height": 685,
        "source": "/beaver-brook/photos/9634279318-large.jpg",
        "photo": true
      },
      "original": {
        "label": "Original",
        "width": 3872,
        "height": 2592,
        "source": "/beaver-brook/photos/9634279318-original.jpg",
        "photo": true
      }
    }
  },
  {
    "id": "9642871180",
    "title": "Dirty Hands",
    "description": "",
    "heightAsPercentageOfWidth": 66,
    "url": "/beaver-brook/photos/9642871180-original.jpg",
    "sizes": {
      "large": {
        "label": "Large",
        "width": 1024,
        "height": 685,
        "source": "/beaver-brook/photos/9642871180-large.jpg",
        "photo": true
      },
      "original": {
        "label": "Original",
        "width": 3872,
        "height": 2592,
        "source": "/beaver-brook/photos/9642871180-original.jpg",
        "photo": true
      }
    }
  },
  {
    "id": "9642817434",
    "title": "Kik and the Boys",
    "description": "",
    "heightAsPercentageOfWidth": 66,
    "url": "/beaver-brook/photos/9642817434-original.jpg",
    "sizes": {
      "large": {
        "label": "Large",
        "width": 1024,
        "height": 685,
        "source": "/beaver-brook/photos/9642817434-large.jpg",
        "photo": true
      },
      "original": {
        "label": "Original",
        "width": 3872,
        "height": 2592,
        "source": "/beaver-brook/photos/9642817434-original.jpg",
        "photo": true
      }
    }
  },
  {
    "id": "9639526235",
    "title": "North Wall",
    "description": "",
    "heightAsPercentageOfWidth": 66,
    "url": "/beaver-brook/photos/9639526235-original.jpg",
    "sizes": {
      "large": {
        "label": "Large",
        "width": 685,
        "height": 1024,
        "source": "/beaver-brook/photos/9639526235-large.jpg",
        "photo": true
      },
      "original": {
        "label": "Original",
        "width": 3872,
        "height": 2592,
        "source": "/beaver-brook/photos/9639526235-original.jpg",
        "photo": true
      }
    }
  },
  {
    "id": "9642677704",
    "title": "The Stove",
    "description": "",
    "heightAsPercentageOfWidth": 66,
    "url": "/beaver-brook/photos/9642677704-original.jpg",
    "sizes": {
      "large": {
        "label": "Large",
        "width": 685,
        "height": 1024,
        "source": "/beaver-brook/photos/9642677704-large.jpg",
        "photo": true
      },
      "original": {
        "label": "Original",
        "width": 3872,
        "height": 2592,
        "source": "/beaver-brook/photos/9642677704-original.jpg",
        "photo": true
      }
    }
  },
  {
    "id": "9639410105",
    "title": "West Wall",
    "description": "",
    "heightAsPercentageOfWidth": 66,
    "url": "/beaver-brook/photos/9639410105-original.jpg",
    "sizes": {
      "large": {
        "label": "Large",
        "width": 685,
        "height": 1024,
        "source": "/beaver-brook/photos/9639410105-large.jpg",
        "photo": true
      },
      "original": {
        "label": "Original",
        "width": 3872,
        "height": 2592,
        "source": "/beaver-brook/photos/9639410105-original.jpg",
        "photo": true
      }
    }
  },
  {
    "id": "9642624066",
    "title": "Zeke",
    "description": "",
    "heightAsPercentageOfWidth": 66,
    "url": "/beaver-brook/photos/9642624066-original.jpg",
    "sizes": {
      "large": {
        "label": "Large",
        "width": 1024,
        "height": 685,
        "source": "/beaver-brook/photos/9642624066-large.jpg",
        "photo": true
      },
      "original": {
        "label": "Original",
        "width": 3872,
        "height": 2592,
        "source": "/beaver-brook/photos/9642624066-original.jpg",
        "photo": true
      }
    }
  },
  {
    "id": "9648080175",
    "title": "Zeke",
    "description": "",
    "heightAsPercentageOfWidth": 66,
    "url": "/beaver-brook/photos/9648080175-original.jpg",
    "sizes": {
      "large": {
        "label": "Large",
        "width": 1024,
        "height": 685,
        "source": "/beaver-brook/photos/9648080175-large.jpg",
        "photo": true
      },
      "original": {
        "label": "Original",
        "width": 3872,
        "height": 2592,
        "source": "/beaver-brook/photos/9648080175-original.jpg",
        "photo": true
      }
    }
  }
]
